scribit_build_instruments/__init__.py
scribit_build_instruments/diagnostics.py
scribit_build_instruments/filesystem_helpers.py
scribit_build_instruments/platform_helpers.py
scribit_build_instruments-1.0.9.dist-info/METADATA
scribit_build_instruments-1.0.9.dist-info/WHEEL
scribit_build_instruments-1.0.9.dist-info/licenses/LICENSE
scribit_build_instruments-1.0.9.dist-info/RECORD
