Metadata-Version: 2.1
Name: scribit_build_instruments
Version: 1.0.9
Summary: A core module to help the scribit build system
Project-URL: Homepage, https://git.twikit.com/research/laddy/scribit
Project-URL: Bug Tracker, https://git.twikit.com/research/laddy/scribit/-/issues
Author-email: Dave De Breuck <dave.debreuck@twikit.com>
License: Copyright 2022 Twikit
License-File: LICENSE
Classifier: License :: OSI Approved :: MIT License
Classifier: Operating System :: OS Independent
Classifier: Programming Language :: Python :: 3
Requires-Python: >=3.7
